calparse/__init__.py
calparse/calparse.py
calparse-0.4.dist-info/LICENSE
calparse-0.4.dist-info/METADATA
calparse-0.4.dist-info/WHEEL
calparse-0.4.dist-info/top_level.txt
calparse-0.4.dist-info/RECORD
