Metadata-Version: 2.1
Name: calparse
Version: 0.4
Summary: A lightweigh CalDAV parser
Home-page: https://github.com/filipweidemann/calpy
Author: Filip Weidemann
Author-email: filip.weidemann@outlook.de
License: UNKNOWN
Platform: UNKNOWN
Classifier: Programming Language :: Python :: 3
Classifier: License :: OSI Approved :: GNU General Public License v3 (GPLv3)
Classifier: Operating System :: OS Independent
